[{"Comp":"S\u00e9rie B","Temp":2023,"Data":"14-04-2023","Casa":"Guarani","GC":"4","GF":"1","Fora":"Ava\u00ed","Res":"VC","PC":3,"PF":0,"J":1},{"Comp":"S\u00e9rie B","Temp":2023,"Data":"14-04-2023","Casa":"Ituano","GC":"2","GF":"0","Fora":"Cear\u00e1","Res":"VC","PC":3,"PF":0,"J":2},{"Comp":"S\u00e9rie B","Temp":2023,"Data":"15-04-2023","Casa":"Vila Nova-GO","GC":"2","GF":"1","Fora":"Novorizontino","Res":"VC","PC":3,"PF":0,"J":3},{"Comp":"S\u00e9rie B","Temp":2023,"Data":"15-04-2023","Casa":"Mirassol","GC":"1","GF":"0","Fora":"Chapecoense","Res":"VC","PC":3,"PF":0,"J":4},{"Comp":"S\u00e9rie B","Temp":2023,"Data":"15-04-2023","Casa":"Sampaio Corr\u00eaa","GC":"3","GF":"3","Fora":"Atl\u00e9tico-GO","Res":"E","PC":1,"PF":1,"J":5},{"Comp":"S\u00e9rie B","Temp":2023,"Data":"15-04-2023","Casa":"Juventude","GC":"1","GF":"2","Fora":"Botafogo-SP","Res":"VV","PC":0,"PF":3,"J":6},{"Comp":"S\u00e9rie B","Temp":2023,"Data":"16-04-2023","Casa":"Crici\u00fama","GC":"2","GF":"0","Fora":"Tombense","Res":"VC","PC":3,"PF":0,"J":7},{"Comp":"S\u00e9rie B","Temp":2023,"Data":"16-04-2023","Casa":"Vit\u00f3ria","GC":"3","GF":"0","Fora":"Ponte Preta","Res":"VC","PC":3,"PF":0,"J":8},{"Comp":"S\u00e9rie B","Temp":2023,"Data":"16-04-2023","Casa":"Londrina","GC":"1","GF":"0","Fora":"ABC","Res":"VC","PC":3,"PF":0,"J":9},{"Comp":"S\u00e9rie B","Temp":2023,"Data":"21-04-2023","Casa":"Ponte Preta","GC":"1","GF":"2","Fora":"Crici\u00fama","Res":"VV","PC":0,"PF":3,"J":10},{"Comp":"S\u00e9rie B","Temp":2023,"Data":"21-04-2023","Casa":"Botafogo-SP","GC":"1","GF":"0","Fora":"Sampaio Corr\u00eaa","Res":"VC","PC":3,"PF":0,"J":11},{"Comp":"S\u00e9rie B","Temp":2023,"Data":"21-04-2023","Casa":"Atl\u00e9tico-GO","GC":"2","GF":"1","Fora":"CRB","Res":"VC","PC":3,"PF":0,"J":12},{"Comp":"S\u00e9rie B","Temp":2023,"Data":"22-04-2023","Casa":"Tombense","GC":"3","GF":"0","Fora":"Ituano","Res":"VC","PC":3,"PF":0,"J":13},{"Comp":"S\u00e9rie B","Temp":2023,"Data":"22-04-2023","Casa":"Cear\u00e1","GC":"0","GF":"3","Fora":"Guarani","Res":"VV","PC":0,"PF":3,"J":14},{"Comp":"S\u00e9rie B","Temp":2023,"Data":"22-04-2023","Casa":"Ava\u00ed","GC":"1","GF":"0","Fora":"Mirassol","Res":"VC","PC":3,"PF":0,"J":15},{"Comp":"S\u00e9rie B","Temp":2023,"Data":"22-04-2023","Casa":"Novorizontino","GC":"1","GF":"0","Fora":"Juventude","Res":"VC","PC":3,"PF":0,"J":16},{"Comp":"S\u00e9rie B","Temp":2023,"Data":"23-04-2023","Casa":"Chapecoense","GC":"3","GF":"0","Fora":"Londrina","Res":"VC","PC":3,"PF":0,"J":17},{"Comp":"S\u00e9rie B","Temp":2023,"Data":"23-04-2023","Casa":"ABC","GC":"0","GF":"3","Fora":"Vit\u00f3ria","Res":"VV","PC":0,"PF":3,"J":18},{"Comp":"S\u00e9rie B","Temp":2023,"Data":"28-04-2023","Casa":"Guarani","GC":"1","GF":"0","Fora":"Ituano","Res":"VC","PC":3,"PF":0,"J":19},{"Comp":"S\u00e9rie B","Temp":2023,"Data":"28-04-2023","Casa":"Crici\u00fama","GC":"1","GF":"0","Fora":"Ava\u00ed","Res":"VC","PC":3,"PF":0,"J":20},{"Comp":"S\u00e9rie B","Temp":2023,"Data":"28-04-2023","Casa":"Vit\u00f3ria","GC":"2","GF":"0","Fora":"Londrina","Res":"VC","PC":3,"PF":0,"J":21},{"Comp":"S\u00e9rie B","Temp":2023,"Data":"29-04-2023","Casa":"Botafogo-SP","GC":"2","GF":"0","Fora":"CRB","Res":"VC","PC":3,"PF":0,"J":22},{"Comp":"S\u00e9rie B","Temp":2023,"Data":"29-04-2023","Casa":"Sampaio Corr\u00eaa","GC":"1","GF":"3","Fora":"Mirassol","Res":"VV","PC":0,"PF":3,"J":23},{"Comp":"S\u00e9rie B","Temp":2023,"Data":"29-04-2023","Casa":"Chapecoense","GC":"1","GF":"1","Fora":"Ponte Preta","Res":"E","PC":1,"PF":1,"J":24},{"Comp":"S\u00e9rie B","Temp":2023,"Data":"29-04-2023","Casa":"Tombense","GC":"1","GF":"1","Fora":"Atl\u00e9tico-GO","Res":"E","PC":1,"PF":1,"J":25},{"Comp":"S\u00e9rie B","Temp":2023,"Data":"30-04-2023","Casa":"Vila Nova-GO","GC":"1","GF":"0","Fora":"Juventude","Res":"VC","PC":3,"PF":0,"J":26},{"Comp":"S\u00e9rie B","Temp":2023,"Data":"30-04-2023","Casa":"Novorizontino","GC":"0","GF":"0","Fora":"Sport","Res":"E","PC":1,"PF":1,"J":27},{"Comp":"S\u00e9rie B","Temp":2023,"Data":"30-04-2023","Casa":"ABC","GC":"1","GF":"2","Fora":"Cear\u00e1","Res":"VV","PC":0,"PF":3,"J":28},{"Comp":"S\u00e9rie B","Temp":2023,"Data":"01-05-2023","Casa":"Londrina","GC":"1","GF":"1","Fora":"Crici\u00fama","Res":"E","PC":1,"PF":1,"J":29},{"Comp":"S\u00e9rie B","Temp":2023,"Data":"02-05-2023","Casa":"CRB","GC":"0","GF":"0","Fora":"Sampaio Corr\u00eaa","Res":"E","PC":1,"PF":1,"J":30},{"Comp":"S\u00e9rie B","Temp":2023,"Data":"02-05-2023","Casa":"Atl\u00e9tico-GO","GC":"2","GF":"1","Fora":"Chapecoense","Res":"VC","PC":3,"PF":0,"J":31},{"Comp":"S\u00e9rie B","Temp":2023,"Data":"02-05-2023","Casa":"Ponte Preta","GC":"2","GF":"0","Fora":"Botafogo-SP","Res":"VC","PC":3,"PF":0,"J":32},{"Comp":"S\u00e9rie B","Temp":2023,"Data":"03-05-2023","Casa":"Ava\u00ed","GC":"0","GF":"3","Fora":"Vila Nova-GO","Res":"VV","PC":0,"PF":3,"J":33},{"Comp":"S\u00e9rie B","Temp":2023,"Data":"03-05-2023","Casa":"Ituano","GC":"3","GF":"0","Fora":"ABC","Res":"VC","PC":3,"PF":0,"J":34},{"Comp":"S\u00e9rie B","Temp":2023,"Data":"03-05-2023","Casa":"Mirassol","GC":"0","GF":"2","Fora":"Novorizontino","Res":"VV","PC":0,"PF":3,"J":35},{"Comp":"S\u00e9rie B","Temp":2023,"Data":"03-05-2023","Casa":"Juventude","GC":"1","GF":"0","Fora":"Guarani","Res":"VC","PC":3,"PF":0,"J":36},{"Comp":"S\u00e9rie B","Temp":2023,"Data":"05-05-2023","Casa":"Botafogo-SP","GC":"0","GF":"3","Fora":"Vit\u00f3ria","Res":"VV","PC":0,"PF":3,"J":37},{"Comp":"S\u00e9rie B","Temp":2023,"Data":"06-05-2023","Casa":"Crici\u00fama","GC":"2","GF":"1","Fora":"Ituano","Res":"VC","PC":3,"PF":0,"J":38},{"Comp":"S\u00e9rie B","Temp":2023,"Data":"06-05-2023","Casa":"Sampaio Corr\u00eaa","GC":"2","GF":"1","Fora":"Juventude","Res":"VC","PC":3,"PF":0,"J":39},{"Comp":"S\u00e9rie B","Temp":2023,"Data":"06-05-2023","Casa":"Chapecoense","GC":"1","GF":"1","Fora":"Novorizontino","Res":"E","PC":1,"PF":1,"J":40},{"Comp":"S\u00e9rie B","Temp":2023,"Data":"06-05-2023","Casa":"Tombense","GC":"0","GF":"1","Fora":"Ava\u00ed","Res":"VV","PC":0,"PF":3,"J":41},{"Comp":"S\u00e9rie B","Temp":2023,"Data":"06-05-2023","Casa":"CRB","GC":"1","GF":"1","Fora":"ABC","Res":"E","PC":1,"PF":1,"J":42},{"Comp":"S\u00e9rie B","Temp":2023,"Data":"06-05-2023","Casa":"Mirassol","GC":"1","GF":"1","Fora":"Vila Nova-GO","Res":"E","PC":1,"PF":1,"J":43},{"Comp":"S\u00e9rie B","Temp":2023,"Data":"07-05-2023","Casa":"Ponte Preta","GC":"0","GF":"0","Fora":"Cear\u00e1","Res":"E","PC":1,"PF":1,"J":44},{"Comp":"S\u00e9rie B","Temp":2023,"Data":"07-05-2023","Casa":"Sport","GC":"2","GF":"0","Fora":"Guarani","Res":"VC","PC":3,"PF":0,"J":45},{"Comp":"S\u00e9rie B","Temp":2023,"Data":"08-05-2023","Casa":"Atl\u00e9tico-GO","GC":"2","GF":"1","Fora":"Londrina","Res":"VC","PC":3,"PF":0,"J":46},{"Comp":"S\u00e9rie B","Temp":2023,"Data":"10-05-2023","Casa":"Cear\u00e1","GC":"0","GF":"2","Fora":"Vit\u00f3ria","Res":"VV","PC":0,"PF":3,"J":47},{"Comp":"S\u00e9rie B","Temp":2023,"Data":"10-05-2023","Casa":"Sport","GC":"3","GF":"2","Fora":"Tombense","Res":"VC","PC":3,"PF":0,"J":48},{"Comp":"S\u00e9rie B","Temp":2023,"Data":"12-05-2023","Casa":"Vila Nova-GO","GC":"0","GF":"0","Fora":"Crici\u00fama","Res":"E","PC":1,"PF":1,"J":49},{"Comp":"S\u00e9rie B","Temp":2023,"Data":"12-05-2023","Casa":"Ava\u00ed","GC":"1","GF":"4","Fora":"Chapecoense","Res":"VV","PC":0,"PF":3,"J":50},{"Comp":"S\u00e9rie B","Temp":2023,"Data":"13-05-2023","Casa":"Guarani","GC":"2","GF":"0","Fora":"Sampaio Corr\u00eaa","Res":"VC","PC":3,"PF":0,"J":51},{"Comp":"S\u00e9rie B","Temp":2023,"Data":"13-05-2023","Casa":"Novorizontino","GC":"0","GF":"1","Fora":"CRB","Res":"VV","PC":0,"PF":3,"J":52},{"Comp":"S\u00e9rie B","Temp":2023,"Data":"13-05-2023","Casa":"Cear\u00e1","GC":"2","GF":"0","Fora":"Tombense","Res":"VC","PC":3,"PF":0,"J":53},{"Comp":"S\u00e9rie B","Temp":2023,"Data":"13-05-2023","Casa":"Juventude","GC":"0","GF":"1","Fora":"Mirassol","Res":"VV","PC":0,"PF":3,"J":54},{"Comp":"S\u00e9rie B","Temp":2023,"Data":"14-05-2023","Casa":"Vit\u00f3ria","GC":"2","GF":"3","Fora":"Atl\u00e9tico-GO","Res":"VV","PC":0,"PF":3,"J":55},{"Comp":"S\u00e9rie B","Temp":2023,"Data":"14-05-2023","Casa":"Londrina","GC":"3","GF":"0","Fora":"Ponte Preta","Res":"VC","PC":3,"PF":0,"J":56},{"Comp":"S\u00e9rie B","Temp":2023,"Data":"14-05-2023","Casa":"ABC","GC":"1","GF":"2","Fora":"Botafogo-SP","Res":"VV","PC":0,"PF":3,"J":57},{"Comp":"S\u00e9rie B","Temp":2023,"Data":"14-05-2023","Casa":"Ituano","GC":"1","GF":"1","Fora":"Sport","Res":"E","PC":1,"PF":1,"J":58},{"Comp":"S\u00e9rie B","Temp":2023,"Data":"19-05-2023","Casa":"Mirassol","GC":"2","GF":"0","Fora":"Vit\u00f3ria","Res":"VC","PC":3,"PF":0,"J":59},{"Comp":"S\u00e9rie B","Temp":2023,"Data":"19-05-2023","Casa":"Atl\u00e9tico-GO","GC":"0","GF":"0","Fora":"Ava\u00ed","Res":"E","PC":1,"PF":1,"J":60},{"Comp":"S\u00e9rie B","Temp":2023,"Data":"19-05-2023","Casa":"Tombense","GC":"0","GF":"2","Fora":"Londrina","Res":"VV","PC":0,"PF":3,"J":61},{"Comp":"S\u00e9rie B","Temp":2023,"Data":"20-05-2023","Casa":"Sampaio Corr\u00eaa","GC":"1","GF":"0","Fora":"ABC","Res":"VC","PC":3,"PF":0,"J":62},{"Comp":"S\u00e9rie B","Temp":2023,"Data":"20-05-2023","Casa":"Sport","GC":"3","GF":"0","Fora":"Botafogo-SP","Res":"VC","PC":3,"PF":0,"J":63},{"Comp":"S\u00e9rie B","Temp":2023,"Data":"20-05-2023","Casa":"Ituano","GC":"0","GF":"2","Fora":"Novorizontino","Res":"VV","PC":0,"PF":3,"J":64},{"Comp":"S\u00e9rie B","Temp":2023,"Data":"21-05-2023","Casa":"Ponte Preta","GC":"1","GF":"1","Fora":"Guarani","Res":"E","PC":1,"PF":1,"J":65},{"Comp":"S\u00e9rie B","Temp":2023,"Data":"21-05-2023","Casa":"Crici\u00fama","GC":"1","GF":"2","Fora":"Cear\u00e1","Res":"VV","PC":0,"PF":3,"J":66},{"Comp":"S\u00e9rie B","Temp":2023,"Data":"21-05-2023","Casa":"Chapecoense","GC":"0","GF":"2","Fora":"Juventude","Res":"VV","PC":0,"PF":3,"J":67},{"Comp":"S\u00e9rie B","Temp":2023,"Data":"21-05-2023","Casa":"CRB","GC":"0","GF":"3","Fora":"Vila Nova-GO","Res":"VV","PC":0,"PF":3,"J":68},{"Comp":"S\u00e9rie B","Temp":2023,"Data":"23-05-2023","Casa":"Botafogo-SP","GC":"1","GF":"0","Fora":"Mirassol","Res":"VC","PC":3,"PF":0,"J":69},{"Comp":"S\u00e9rie B","Temp":2023,"Data":"23-05-2023","Casa":"Novorizontino","GC":"2","GF":"0","Fora":"Ava\u00ed","Res":"VC","PC":3,"PF":0,"J":70},{"Comp":"S\u00e9rie B","Temp":2023,"Data":"23-05-2023","Casa":"ABC","GC":"1","GF":"0","Fora":"Tombense","Res":"VC","PC":3,"PF":0,"J":71},{"Comp":"S\u00e9rie B","Temp":2023,"Data":"24-05-2023","Casa":"Sampaio Corr\u00eaa","GC":"0","GF":"0","Fora":"Ponte Preta","Res":"E","PC":1,"PF":1,"J":72},{"Comp":"S\u00e9rie B","Temp":2023,"Data":"24-05-2023","Casa":"Londrina","GC":"1","GF":"3","Fora":"Cear\u00e1","Res":"VV","PC":0,"PF":3,"J":73},{"Comp":"S\u00e9rie B","Temp":2023,"Data":"24-05-2023","Casa":"Juventude","GC":"3","GF":"0","Fora":"Atl\u00e9tico-GO","Res":"VC","PC":3,"PF":0,"J":74},{"Comp":"S\u00e9rie B","Temp":2023,"Data":"24-05-2023","Casa":"Guarani","GC":"3","GF":"3","Fora":"Chapecoense","Res":"E","PC":1,"PF":1,"J":75},{"Comp":"S\u00e9rie B","Temp":2023,"Data":"24-05-2023","Casa":"Crici\u00fama","GC":"1","GF":"0","Fora":"Sport","Res":"VC","PC":3,"PF":0,"J":76},{"Comp":"S\u00e9rie B","Temp":2023,"Data":"24-05-2023","Casa":"Vila Nova-GO","GC":"1","GF":"0","Fora":"Ituano","Res":"VC","PC":3,"PF":0,"J":77},{"Comp":"S\u00e9rie B","Temp":2023,"Data":"24-05-2023","Casa":"Vit\u00f3ria","GC":"1","GF":"0","Fora":"CRB","Res":"VC","PC":3,"PF":0,"J":78},{"Comp":"S\u00e9rie B","Temp":2023,"Data":"27-05-2023","Casa":"CRB","GC":"1","GF":"2","Fora":"Juventude","Res":"VV","PC":0,"PF":3,"J":79},{"Comp":"S\u00e9rie B","Temp":2023,"Data":"27-05-2023","Casa":"Ituano","GC":"3","GF":"1","Fora":"Londrina","Res":"VC","PC":3,"PF":0,"J":80},{"Comp":"S\u00e9rie B","Temp":2023,"Data":"27-05-2023","Casa":"Atl\u00e9tico-GO","GC":"1","GF":"1","Fora":"Botafogo-SP","Res":"E","PC":1,"PF":1,"J":81},{"Comp":"S\u00e9rie B","Temp":2023,"Data":"27-05-2023","Casa":"Ava\u00ed","GC":"1","GF":"1","Fora":"Vit\u00f3ria","Res":"E","PC":1,"PF":1,"J":82},{"Comp":"S\u00e9rie B","Temp":2023,"Data":"28-05-2023","Casa":"Ponte Preta","GC":"1","GF":"0","Fora":"Vila Nova-GO","Res":"VC","PC":3,"PF":0,"J":83},{"Comp":"S\u00e9rie B","Temp":2023,"Data":"28-05-2023","Casa":"Mirassol","GC":"1","GF":"0","Fora":"Crici\u00fama","Res":"VC","PC":3,"PF":0,"J":84},{"Comp":"S\u00e9rie B","Temp":2023,"Data":"28-05-2023","Casa":"Sport","GC":"4","GF":"1","Fora":"ABC","Res":"VC","PC":3,"PF":0,"J":85},{"Comp":"S\u00e9rie B","Temp":2023,"Data":"28-05-2023","Casa":"Cear\u00e1","GC":"0","GF":"3","Fora":"Novorizontino","Res":"VV","PC":0,"PF":3,"J":86},{"Comp":"S\u00e9rie B","Temp":2023,"Data":"28-05-2023","Casa":"Tombense","GC":"1","GF":"1","Fora":"Guarani","Res":"E","PC":1,"PF":1,"J":87},{"Comp":"S\u00e9rie B","Temp":2023,"Data":"29-05-2023","Casa":"Chapecoense","GC":"0","GF":"1","Fora":"Sampaio Corr\u00eaa","Res":"VV","PC":0,"PF":3,"J":88},{"Comp":"S\u00e9rie B","Temp":2023,"Data":"02-06-2023","Casa":"Vit\u00f3ria","GC":"3","GF":"0","Fora":"Ituano","Res":"VC","PC":3,"PF":0,"J":89},{"Comp":"S\u00e9rie B","Temp":2023,"Data":"02-06-2023","Casa":"Cear\u00e1","GC":"2","GF":"0","Fora":"Chapecoense","Res":"VC","PC":3,"PF":0,"J":90},{"Comp":"S\u00e9rie B","Temp":2023,"Data":"02-06-2023","Casa":"Crici\u00fama","GC":"3","GF":"0","Fora":"Atl\u00e9tico-GO","Res":"VC","PC":3,"PF":0,"J":91},{"Comp":"S\u00e9rie B","Temp":2023,"Data":"02-06-2023","Casa":"Botafogo-SP","GC":"0","GF":"0","Fora":"Tombense","Res":"E","PC":1,"PF":1,"J":92},{"Comp":"S\u00e9rie B","Temp":2023,"Data":"03-06-2023","Casa":"ABC","GC":"0","GF":"1","Fora":"Novorizontino","Res":"VV","PC":0,"PF":3,"J":93},{"Comp":"S\u00e9rie B","Temp":2023,"Data":"03-06-2023","Casa":"Juventude","GC":"3","GF":"2","Fora":"Ava\u00ed","Res":"VC","PC":3,"PF":0,"J":94},{"Comp":"S\u00e9rie B","Temp":2023,"Data":"03-06-2023","Casa":"Vila Nova-GO","GC":"3","GF":"0","Fora":"Sampaio Corr\u00eaa","Res":"VC","PC":3,"PF":0,"J":95},{"Comp":"S\u00e9rie B","Temp":2023,"Data":"03-06-2023","Casa":"Mirassol","GC":"1","GF":"0","Fora":"Ponte Preta","Res":"VC","PC":3,"PF":0,"J":96},{"Comp":"S\u00e9rie B","Temp":2023,"Data":"04-06-2023","Casa":"Guarani","GC":"0","GF":"1","Fora":"CRB","Res":"VV","PC":0,"PF":3,"J":97},{"Comp":"S\u00e9rie B","Temp":2023,"Data":"04-06-2023","Casa":"Londrina","GC":"1","GF":"2","Fora":"Sport","Res":"VV","PC":0,"PF":3,"J":98},{"Comp":"S\u00e9rie B","Temp":2023,"Data":"06-06-2023","Casa":"Ponte Preta","GC":"0","GF":"0","Fora":"ABC","Res":"E","PC":1,"PF":1,"J":99},{"Comp":"S\u00e9rie B","Temp":2023,"Data":"06-06-2023","Casa":"Atl\u00e9tico-GO","GC":"0","GF":"3","Fora":"Cear\u00e1","Res":"VV","PC":0,"PF":3,"J":100},{"Comp":"S\u00e9rie B","Temp":2023,"Data":"06-06-2023","Casa":"Botafogo-SP","GC":"0","GF":"2","Fora":"Ituano","Res":"VV","PC":0,"PF":3,"J":101},{"Comp":"S\u00e9rie B","Temp":2023,"Data":"06-06-2023","Casa":"Chapecoense","GC":"0","GF":"1","Fora":"Vila Nova-GO","Res":"VV","PC":0,"PF":3,"J":102},{"Comp":"S\u00e9rie B","Temp":2023,"Data":"06-06-2023","Casa":"Tombense","GC":"1","GF":"2","Fora":"Vit\u00f3ria","Res":"VV","PC":0,"PF":3,"J":103},{"Comp":"S\u00e9rie B","Temp":2023,"Data":"07-06-2023","Casa":"CRB","GC":"2","GF":"0","Fora":"Mirassol","Res":"VC","PC":3,"PF":0,"J":104},{"Comp":"S\u00e9rie B","Temp":2023,"Data":"07-06-2023","Casa":"Novorizontino","GC":"1","GF":"0","Fora":"Guarani","Res":"VC","PC":3,"PF":0,"J":105},{"Comp":"S\u00e9rie B","Temp":2023,"Data":"07-06-2023","Casa":"Sport","GC":"2","GF":"1","Fora":"Ava\u00ed","Res":"VC","PC":3,"PF":0,"J":106},{"Comp":"S\u00e9rie B","Temp":2023,"Data":"07-06-2023","Casa":"Sampaio Corr\u00eaa","GC":"2","GF":"0","Fora":"Londrina","Res":"VC","PC":3,"PF":0,"J":107},{"Comp":"S\u00e9rie B","Temp":2023,"Data":"08-06-2023","Casa":"Crici\u00fama","GC":"0","GF":"1","Fora":"Juventude","Res":"VV","PC":0,"PF":3,"J":108},{"Comp":"S\u00e9rie B","Temp":2023,"Data":"09-06-2023","Casa":"ABC","GC":"1","GF":"1","Fora":"Chapecoense","Res":"E","PC":1,"PF":1,"J":109},{"Comp":"S\u00e9rie B","Temp":2023,"Data":"10-06-2023","Casa":"Vila Nova-GO","GC":"0","GF":"0","Fora":"Guarani","Res":"E","PC":1,"PF":1,"J":110},{"Comp":"S\u00e9rie B","Temp":2023,"Data":"10-06-2023","Casa":"Ituano","GC":"1","GF":"1","Fora":"Atl\u00e9tico-GO","Res":"E","PC":1,"PF":1,"J":111},{"Comp":"S\u00e9rie B","Temp":2023,"Data":"10-06-2023","Casa":"Novorizontino","GC":"1","GF":"0","Fora":"Sampaio Corr\u00eaa","Res":"VC","PC":3,"PF":0,"J":112},{"Comp":"S\u00e9rie B","Temp":2023,"Data":"10-06-2023","Casa":"Cear\u00e1","GC":"1","GF":"3","Fora":"CRB","Res":"VV","PC":0,"PF":3,"J":113},{"Comp":"S\u00e9rie B","Temp":2023,"Data":"11-06-2023","Casa":"Ponte Preta","GC":"1","GF":"1","Fora":"Sport","Res":"E","PC":1,"PF":1,"J":114},{"Comp":"S\u00e9rie B","Temp":2023,"Data":"11-06-2023","Casa":"Ava\u00ed","GC":"1","GF":"1","Fora":"Botafogo-SP","Res":"E","PC":1,"PF":1,"J":115},{"Comp":"S\u00e9rie B","Temp":2023,"Data":"11-06-2023","Casa":"Vit\u00f3ria","GC":"0","GF":"1","Fora":"Crici\u00fama","Res":"VV","PC":0,"PF":3,"J":116},{"Comp":"S\u00e9rie B","Temp":2023,"Data":"11-06-2023","Casa":"Juventude","GC":"1","GF":"2","Fora":"Tombense","Res":"VV","PC":0,"PF":3,"J":117},{"Comp":"S\u00e9rie B","Temp":2023,"Data":"11-06-2023","Casa":"Londrina","GC":"1","GF":"2","Fora":"Mirassol","Res":"VV","PC":0,"PF":3,"J":118},{"Comp":"S\u00e9rie B","Temp":2023,"Data":"18-06-2023","Casa":"Sport","GC":"1","GF":"0","Fora":"Vila Nova-GO","Res":"VC","PC":3,"PF":0,"J":119},{"Comp":"S\u00e9rie B","Temp":2023,"Data":"21-06-2023","Casa":"CRB","GC":"2","GF":"2","Fora":"Ituano","Res":"E","PC":1,"PF":1,"J":120},{"Comp":"S\u00e9rie B","Temp":2023,"Data":"22-06-2023","Casa":"Sport","GC":"3","GF":"0","Fora":"Juventude","Res":"VC","PC":3,"PF":0,"J":121},{"Comp":"S\u00e9rie B","Temp":2023,"Data":"23-06-2023","Casa":"Atl\u00e9tico-GO","GC":"1","GF":"0","Fora":"Ponte Preta","Res":"VC","PC":3,"PF":0,"J":122},{"Comp":"S\u00e9rie B","Temp":2023,"Data":"24-06-2023","Casa":"Tombense","GC":"1","GF":"2","Fora":"Novorizontino","Res":"VV","PC":0,"PF":3,"J":123},{"Comp":"S\u00e9rie B","Temp":2023,"Data":"24-06-2023","Casa":"Chapecoense","GC":"1","GF":"1","Fora":"Crici\u00fama","Res":"E","PC":1,"PF":1,"J":124},{"Comp":"S\u00e9rie B","Temp":2023,"Data":"24-06-2023","Casa":"Botafogo-SP","GC":"0","GF":"3","Fora":"Vila Nova-GO","Res":"VV","PC":0,"PF":3,"J":125},{"Comp":"S\u00e9rie B","Temp":2023,"Data":"24-06-2023","Casa":"Ava\u00ed","GC":"0","GF":"0","Fora":"Londrina","Res":"E","PC":1,"PF":1,"J":126},{"Comp":"S\u00e9rie B","Temp":2023,"Data":"25-06-2023","Casa":"Guarani","GC":"2","GF":"0","Fora":"Vit\u00f3ria","Res":"VC","PC":3,"PF":0,"J":127},{"Comp":"S\u00e9rie B","Temp":2023,"Data":"25-06-2023","Casa":"Mirassol","GC":"3","GF":"2","Fora":"ABC","Res":"VC","PC":3,"PF":0,"J":128},{"Comp":"S\u00e9rie B","Temp":2023,"Data":"25-06-2023","Casa":"Sampaio Corr\u00eaa","GC":"1","GF":"1","Fora":"Cear\u00e1","Res":"E","PC":1,"PF":1,"J":129},{"Comp":"S\u00e9rie B","Temp":2023,"Data":"27-06-2023","Casa":"Vila Nova-GO","GC":"1","GF":"0","Fora":"Tombense","Res":"VC","PC":3,"PF":0,"J":130},{"Comp":"S\u00e9rie B","Temp":2023,"Data":"27-06-2023","Casa":"Crici\u00fama","GC":"2","GF":"1","Fora":"CRB","Res":"VC","PC":3,"PF":0,"J":131},{"Comp":"S\u00e9rie B","Temp":2023,"Data":"27-06-2023","Casa":"Novorizontino","GC":"0","GF":"1","Fora":"Botafogo-SP","Res":"VV","PC":0,"PF":3,"J":132},{"Comp":"S\u00e9rie B","Temp":2023,"Data":"27-06-2023","Casa":"Chapecoense","GC":"1","GF":"1","Fora":"Sport","Res":"E","PC":1,"PF":1,"J":133},{"Comp":"S\u00e9rie B","Temp":2023,"Data":"28-06-2023","Casa":"Londrina","GC":"1","GF":"2","Fora":"Juventude","Res":"VV","PC":0,"PF":3,"J":134},{"Comp":"S\u00e9rie B","Temp":2023,"Data":"28-06-2023","Casa":"Cear\u00e1","GC":"0","GF":"0","Fora":"Ava\u00ed","Res":"E","PC":1,"PF":1,"J":135},{"Comp":"S\u00e9rie B","Temp":2023,"Data":"28-06-2023","Casa":"ABC","GC":"1","GF":"1","Fora":"Atl\u00e9tico-GO","Res":"E","PC":1,"PF":1,"J":136},{"Comp":"S\u00e9rie B","Temp":2023,"Data":"28-06-2023","Casa":"Ituano","GC":"0","GF":"1","Fora":"Ponte Preta","Res":"VV","PC":0,"PF":3,"J":137},{"Comp":"S\u00e9rie B","Temp":2023,"Data":"28-06-2023","Casa":"Guarani","GC":"2","GF":"1","Fora":"Mirassol","Res":"VC","PC":3,"PF":0,"J":138},{"Comp":"S\u00e9rie B","Temp":2023,"Data":"28-06-2023","Casa":"Vit\u00f3ria","GC":"2","GF":"1","Fora":"Sampaio Corr\u00eaa","Res":"VC","PC":3,"PF":0,"J":139},{"Comp":"S\u00e9rie B","Temp":2023,"Data":"30-06-2023","Casa":"Tombense","GC":"4","GF":"2","Fora":"Chapecoense","Res":"VC","PC":3,"PF":0,"J":140},{"Comp":"S\u00e9rie B","Temp":2023,"Data":"01-07-2023","Casa":"Atl\u00e9tico-GO","GC":"1","GF":"1","Fora":"Vila Nova-GO","Res":"E","PC":1,"PF":1,"J":141},{"Comp":"S\u00e9rie B","Temp":2023,"Data":"01-07-2023","Casa":"Ava\u00ed","GC":"0","GF":"2","Fora":"ABC","Res":"VV","PC":0,"PF":3,"J":142},{"Comp":"S\u00e9rie B","Temp":2023,"Data":"01-07-2023","Casa":"Sampaio Corr\u00eaa","GC":"0","GF":"2","Fora":"Crici\u00fama","Res":"VV","PC":0,"PF":3,"J":143},{"Comp":"S\u00e9rie B","Temp":2023,"Data":"01-07-2023","Casa":"CRB","GC":"2","GF":"1","Fora":"Londrina","Res":"VC","PC":3,"PF":0,"J":144},{"Comp":"S\u00e9rie B","Temp":2023,"Data":"02-07-2023","Casa":"Juventude","GC":"1","GF":"0","Fora":"Vit\u00f3ria","Res":"VC","PC":3,"PF":0,"J":145},{"Comp":"S\u00e9rie B","Temp":2023,"Data":"02-07-2023","Casa":"Ponte Preta","GC":"1","GF":"0","Fora":"Novorizontino","Res":"VC","PC":3,"PF":0,"J":146},{"Comp":"S\u00e9rie B","Temp":2023,"Data":"02-07-2023","Casa":"Sport","GC":"2","GF":"0","Fora":"Cear\u00e1","Res":"VC","PC":3,"PF":0,"J":147},{"Comp":"S\u00e9rie B","Temp":2023,"Data":"03-07-2023","Casa":"Botafogo-SP","GC":"1","GF":"0","Fora":"Guarani","Res":"VC","PC":3,"PF":0,"J":148},{"Comp":"S\u00e9rie B","Temp":2023,"Data":"03-07-2023","Casa":"Mirassol","GC":"0","GF":"1","Fora":"Ituano","Res":"VV","PC":0,"PF":3,"J":149},{"Comp":"S\u00e9rie B","Temp":2023,"Data":"05-07-2023","Casa":"CRB","GC":"2","GF":"0","Fora":"Sport","Res":"VC","PC":3,"PF":0,"J":150},{"Comp":"S\u00e9rie B","Temp":2023,"Data":"07-07-2023","Casa":"Novorizontino","GC":"2","GF":"2","Fora":"Atl\u00e9tico-GO","Res":"E","PC":1,"PF":1,"J":151},{"Comp":"S\u00e9rie B","Temp":2023,"Data":"07-07-2023","Casa":"Cear\u00e1","GC":"3","GF":"0","Fora":"Botafogo-SP","Res":"VC","PC":3,"PF":0,"J":152},{"Comp":"S\u00e9rie B","Temp":2023,"Data":"08-07-2023","Casa":"Guarani","GC":"2","GF":"1","Fora":"Londrina","Res":"VC","PC":3,"PF":0,"J":153},{"Comp":"S\u00e9rie B","Temp":2023,"Data":"08-07-2023","Casa":"Tombense","GC":"0","GF":"1","Fora":"Sampaio Corr\u00eaa","Res":"VV","PC":0,"PF":3,"J":154},{"Comp":"S\u00e9rie B","Temp":2023,"Data":"08-07-2023","Casa":"ABC","GC":"0","GF":"1","Fora":"Crici\u00fama","Res":"VV","PC":0,"PF":3,"J":155},{"Comp":"S\u00e9rie B","Temp":2023,"Data":"08-07-2023","Casa":"Ava\u00ed","GC":"0","GF":"1","Fora":"Ponte Preta","Res":"VV","PC":0,"PF":3,"J":156},{"Comp":"S\u00e9rie B","Temp":2023,"Data":"08-07-2023","Casa":"Ituano","GC":"1","GF":"1","Fora":"Juventude","Res":"E","PC":1,"PF":1,"J":157},{"Comp":"S\u00e9rie B","Temp":2023,"Data":"09-07-2023","Casa":"Chapecoense","GC":"2","GF":"1","Fora":"CRB","Res":"VC","PC":3,"PF":0,"J":158},{"Comp":"S\u00e9rie B","Temp":2023,"Data":"09-07-2023","Casa":"Sport","GC":"0","GF":"0","Fora":"Mirassol","Res":"E","PC":1,"PF":1,"J":159},{"Comp":"S\u00e9rie B","Temp":2023,"Data":"10-07-2023","Casa":"Vila Nova-GO","GC":"1","GF":"0","Fora":"Vit\u00f3ria","Res":"VC","PC":3,"PF":0,"J":160},{"Comp":"S\u00e9rie B","Temp":2023,"Data":"13-07-2023","Casa":"Crici\u00fama","GC":"1","GF":"1","Fora":"Guarani","Res":"E","PC":1,"PF":1,"J":161},{"Comp":"S\u00e9rie B","Temp":2023,"Data":"14-07-2023","Casa":"Atl\u00e9tico-GO","GC":"3","GF":"1","Fora":"Sport","Res":"VC","PC":3,"PF":0,"J":162},{"Comp":"S\u00e9rie B","Temp":2023,"Data":"14-07-2023","Casa":"Sampaio Corr\u00eaa","GC":"0","GF":"0","Fora":"Ituano","Res":"E","PC":1,"PF":1,"J":163},{"Comp":"S\u00e9rie B","Temp":2023,"Data":"15-07-2023","Casa":"Ponte Preta","GC":"0","GF":"1","Fora":"Tombense","Res":"VV","PC":0,"PF":3,"J":164},{"Comp":"S\u00e9rie B","Temp":2023,"Data":"15-07-2023","Casa":"Juventude","GC":"1","GF":"1","Fora":"ABC","Res":"E","PC":1,"PF":1,"J":165},{"Comp":"S\u00e9rie B","Temp":2023,"Data":"15-07-2023","Casa":"Londrina","GC":"1","GF":"0","Fora":"Vila Nova-GO","Res":"VC","PC":3,"PF":0,"J":166},{"Comp":"S\u00e9rie B","Temp":2023,"Data":"16-07-2023","Casa":"Mirassol","GC":"1","GF":"1","Fora":"Cear\u00e1","Res":"E","PC":1,"PF":1,"J":167},{"Comp":"S\u00e9rie B","Temp":2023,"Data":"16-07-2023","Casa":"Vit\u00f3ria","GC":"2","GF":"1","Fora":"Novorizontino","Res":"VC","PC":3,"PF":0,"J":168},{"Comp":"S\u00e9rie B","Temp":2023,"Data":"17-07-2023","Casa":"Botafogo-SP","GC":"1","GF":"0","Fora":"Crici\u00fama","Res":"VC","PC":3,"PF":0,"J":169},{"Comp":"S\u00e9rie B","Temp":2023,"Data":"18-07-2023","Casa":"Chapecoense","GC":"1","GF":"0","Fora":"Ituano","Res":"VC","PC":3,"PF":0,"J":170},{"Comp":"S\u00e9rie B","Temp":2023,"Data":"18-07-2023","Casa":"Tombense","GC":"2","GF":"1","Fora":"CRB","Res":"VC","PC":3,"PF":0,"J":171},{"Comp":"S\u00e9rie B","Temp":2023,"Data":"18-07-2023","Casa":"Ponte Preta","GC":"0","GF":"0","Fora":"Juventude","Res":"E","PC":1,"PF":1,"J":172},{"Comp":"S\u00e9rie B","Temp":2023,"Data":"19-07-2023","Casa":"Atl\u00e9tico-GO","GC":"2","GF":"2","Fora":"Mirassol","Res":"E","PC":1,"PF":1,"J":173},{"Comp":"S\u00e9rie B","Temp":2023,"Data":"19-07-2023","Casa":"Ava\u00ed","GC":"2","GF":"0","Fora":"Sampaio Corr\u00eaa","Res":"VC","PC":3,"PF":0,"J":174},{"Comp":"S\u00e9rie B","Temp":2023,"Data":"19-07-2023","Casa":"Novorizontino","GC":"3","GF":"0","Fora":"Londrina","Res":"VC","PC":3,"PF":0,"J":175},{"Comp":"S\u00e9rie B","Temp":2023,"Data":"19-07-2023","Casa":"Sport","GC":"1","GF":"2","Fora":"Vit\u00f3ria","Res":"VV","PC":0,"PF":3,"J":176},{"Comp":"S\u00e9rie B","Temp":2023,"Data":"19-07-2023","Casa":"Cear\u00e1","GC":"1","GF":"0","Fora":"Vila Nova-GO","Res":"VC","PC":3,"PF":0,"J":177},{"Comp":"S\u00e9rie B","Temp":2023,"Data":"19-07-2023","Casa":"ABC","GC":"0","GF":"1","Fora":"Guarani","Res":"VV","PC":0,"PF":3,"J":178},{"Comp":"S\u00e9rie B","Temp":2023,"Data":"21-07-2023","Casa":"CRB","GC":"1","GF":"0","Fora":"Ponte Preta","Res":"VC","PC":3,"PF":0,"J":179},{"Comp":"S\u00e9rie B","Temp":2023,"Data":"22-07-2023","Casa":"Vila Nova-GO","GC":"1","GF":"1","Fora":"ABC","Res":"E","PC":1,"PF":1,"J":180},{"Comp":"S\u00e9rie B","Temp":2023,"Data":"22-07-2023","Casa":"Crici\u00fama","GC":"0","GF":"1","Fora":"Novorizontino","Res":"VV","PC":0,"PF":3,"J":181},{"Comp":"S\u00e9rie B","Temp":2023,"Data":"22-07-2023","Casa":"Ituano","GC":"0","GF":"1","Fora":"Ava\u00ed","Res":"VV","PC":0,"PF":3,"J":182},{"Comp":"S\u00e9rie B","Temp":2023,"Data":"22-07-2023","Casa":"Mirassol","GC":"2","GF":"0","Fora":"Tombense","Res":"VC","PC":3,"PF":0,"J":183},{"Comp":"S\u00e9rie B","Temp":2023,"Data":"23-07-2023","Casa":"Sampaio Corr\u00eaa","GC":"1","GF":"2","Fora":"Sport","Res":"VV","PC":0,"PF":3,"J":184},{"Comp":"S\u00e9rie B","Temp":2023,"Data":"23-07-2023","Casa":"Juventude","GC":"1","GF":"0","Fora":"Cear\u00e1","Res":"VC","PC":3,"PF":0,"J":185},{"Comp":"S\u00e9rie B","Temp":2023,"Data":"23-07-2023","Casa":"Guarani","GC":"1","GF":"0","Fora":"Atl\u00e9tico-GO","Res":"VC","PC":3,"PF":0,"J":186},{"Comp":"S\u00e9rie B","Temp":2023,"Data":"24-07-2023","Casa":"Londrina","GC":"1","GF":"2","Fora":"Botafogo-SP","Res":"VV","PC":0,"PF":3,"J":187},{"Comp":"S\u00e9rie B","Temp":2023,"Data":"24-07-2023","Casa":"Vit\u00f3ria","GC":"1","GF":"0","Fora":"Chapecoense","Res":"VC","PC":3,"PF":0,"J":188},{"Comp":"S\u00e9rie B","Temp":2023,"Data":"28-07-2023","Casa":"Sport","GC":"2","GF":"0","Fora":"CRB","Res":"VC","PC":3,"PF":0,"J":189},{"Comp":"S\u00e9rie B","Temp":2023,"Data":"28-07-2023","Casa":"Cear\u00e1","GC":"1","GF":"1","Fora":"Ituano","Res":"E","PC":1,"PF":1,"J":190},{"Comp":"S\u00e9rie B","Temp":2023,"Data":"29-07-2023","Casa":"Atl\u00e9tico-GO","GC":"2","GF":"2","Fora":"Sampaio Corr\u00eaa","Res":"E","PC":1,"PF":1,"J":191},{"Comp":"S\u00e9rie B","Temp":2023,"Data":"29-07-2023","Casa":"Ava\u00ed","GC":"1","GF":"2","Fora":"Guarani","Res":"VV","PC":0,"PF":3,"J":192},{"Comp":"S\u00e9rie B","Temp":2023,"Data":"29-07-2023","Casa":"Botafogo-SP","GC":"0","GF":"2","Fora":"Juventude","Res":"VV","PC":0,"PF":3,"J":193},{"Comp":"S\u00e9rie B","Temp":2023,"Data":"29-07-2023","Casa":"Chapecoense","GC":"0","GF":"1","Fora":"Mirassol","Res":"VV","PC":0,"PF":3,"J":194},{"Comp":"S\u00e9rie B","Temp":2023,"Data":"29-07-2023","Casa":"ABC","GC":"0","GF":"0","Fora":"Londrina","Res":"E","PC":1,"PF":1,"J":195},{"Comp":"S\u00e9rie B","Temp":2023,"Data":"30-07-2023","Casa":"Ponte Preta","GC":"2","GF":"2","Fora":"Vit\u00f3ria","Res":"E","PC":1,"PF":1,"J":196},{"Comp":"S\u00e9rie B","Temp":2023,"Data":"30-07-2023","Casa":"Novorizontino","GC":"3","GF":"1","Fora":"Vila Nova-GO","Res":"VC","PC":3,"PF":0,"J":197},{"Comp":"S\u00e9rie B","Temp":2023,"Data":"30-07-2023","Casa":"Tombense","GC":"2","GF":"2","Fora":"Crici\u00fama","Res":"E","PC":1,"PF":1,"J":198},{"Comp":"S\u00e9rie B","Temp":2023,"Data":"01-08-2023","Casa":"Mirassol","GC":"2","GF":"2","Fora":"Ava\u00ed","Res":"E","PC":1,"PF":1,"J":199},{"Comp":"S\u00e9rie B","Temp":2023,"Data":"01-08-2023","Casa":"Sampaio Corr\u00eaa","GC":"0","GF":"0","Fora":"Botafogo-SP","Res":"E","PC":1,"PF":1,"J":200},{"Comp":"S\u00e9rie B","Temp":2023,"Data":"01-08-2023","Casa":"CRB","GC":"2","GF":"1","Fora":"Atl\u00e9tico-GO","Res":"VC","PC":3,"PF":0,"J":201},{"Comp":"S\u00e9rie B","Temp":2023,"Data":"02-08-2023","Casa":"Londrina","GC":"1","GF":"1","Fora":"Chapecoense","Res":"E","PC":1,"PF":1,"J":202},{"Comp":"S\u00e9rie B","Temp":2023,"Data":"02-08-2023","Casa":"Juventude","GC":"1","GF":"0","Fora":"Novorizontino","Res":"VC","PC":3,"PF":0,"J":203},{"Comp":"S\u00e9rie B","Temp":2023,"Data":"02-08-2023","Casa":"Vit\u00f3ria","GC":"2","GF":"0","Fora":"ABC","Res":"VC","PC":3,"PF":0,"J":204},{"Comp":"S\u00e9rie B","Temp":2023,"Data":"02-08-2023","Casa":"Guarani","GC":"0","GF":"0","Fora":"Cear\u00e1","Res":"E","PC":1,"PF":1,"J":205},{"Comp":"S\u00e9rie B","Temp":2023,"Data":"02-08-2023","Casa":"Crici\u00fama","GC":"2","GF":"1","Fora":"Ponte Preta","Res":"VC","PC":3,"PF":0,"J":206},{"Comp":"S\u00e9rie B","Temp":2023,"Data":"02-08-2023","Casa":"Vila Nova-GO","GC":"0","GF":"1","Fora":"Sport","Res":"VV","PC":0,"PF":3,"J":207},{"Comp":"S\u00e9rie B","Temp":2023,"Data":"02-08-2023","Casa":"Ituano","GC":"1","GF":"0","Fora":"Tombense","Res":"VC","PC":3,"PF":0,"J":208},{"Comp":"S\u00e9rie B","Temp":2023,"Data":"04-08-2023","Casa":"Mirassol","GC":"0","GF":"0","Fora":"Sampaio Corr\u00eaa","Res":"E","PC":1,"PF":1,"J":209},{"Comp":"S\u00e9rie B","Temp":2023,"Data":"05-08-2023","Casa":"Ituano","GC":"1","GF":"1","Fora":"Guarani","Res":"E","PC":1,"PF":1,"J":210},{"Comp":"S\u00e9rie B","Temp":2023,"Data":"05-08-2023","Casa":"Sport","GC":"1","GF":"0","Fora":"Novorizontino","Res":"VC","PC":3,"PF":0,"J":211},{"Comp":"S\u00e9rie B","Temp":2023,"Data":"05-08-2023","Casa":"CRB","GC":"0","GF":"0","Fora":"Botafogo-SP","Res":"E","PC":1,"PF":1,"J":212},{"Comp":"S\u00e9rie B","Temp":2023,"Data":"05-08-2023","Casa":"Ava\u00ed","GC":"1","GF":"0","Fora":"Crici\u00fama","Res":"VC","PC":3,"PF":0,"J":213},{"Comp":"S\u00e9rie B","Temp":2023,"Data":"06-08-2023","Casa":"Cear\u00e1","GC":"1","GF":"0","Fora":"ABC","Res":"VC","PC":3,"PF":0,"J":214},{"Comp":"S\u00e9rie B","Temp":2023,"Data":"06-08-2023","Casa":"Ponte Preta","GC":"1","GF":"0","Fora":"Chapecoense","Res":"VC","PC":3,"PF":0,"J":215},{"Comp":"S\u00e9rie B","Temp":2023,"Data":"07-08-2023","Casa":"Juventude","GC":"0","GF":"2","Fora":"Vila Nova-GO","Res":"VV","PC":0,"PF":3,"J":216},{"Comp":"S\u00e9rie B","Temp":2023,"Data":"07-08-2023","Casa":"Londrina","GC":"2","GF":"0","Fora":"Vit\u00f3ria","Res":"VC","PC":3,"PF":0,"J":217},{"Comp":"S\u00e9rie B","Temp":2023,"Data":"07-08-2023","Casa":"Atl\u00e9tico-GO","GC":"3","GF":"2","Fora":"Tombense","Res":"VC","PC":3,"PF":0,"J":218},{"Comp":"S\u00e9rie B","Temp":2023,"Data":"11-08-2023","Casa":"Novorizontino","GC":"2","GF":"1","Fora":"Mirassol","Res":"VC","PC":3,"PF":0,"J":219},{"Comp":"S\u00e9rie B","Temp":2023,"Data":"11-08-2023","Casa":"Tombense","GC":"0","GF":"0","Fora":"Sport","Res":"E","PC":1,"PF":1,"J":220},{"Comp":"S\u00e9rie B","Temp":2023,"Data":"12-08-2023","Casa":"Vila Nova-GO","GC":"1","GF":"1","Fora":"Ava\u00ed","Res":"E","PC":1,"PF":1,"J":221},{"Comp":"S\u00e9rie B","Temp":2023,"Data":"12-08-2023","Casa":"Crici\u00fama","GC":"2","GF":"0","Fora":"Londrina","Res":"VC","PC":3,"PF":0,"J":222},{"Comp":"S\u00e9rie B","Temp":2023,"Data":"12-08-2023","Casa":"Botafogo-SP","GC":"0","GF":"0","Fora":"Ponte Preta","Res":"E","PC":1,"PF":1,"J":223},{"Comp":"S\u00e9rie B","Temp":2023,"Data":"12-08-2023","Casa":"Sampaio Corr\u00eaa","GC":"1","GF":"1","Fora":"CRB","Res":"E","PC":1,"PF":1,"J":224},{"Comp":"S\u00e9rie B","Temp":2023,"Data":"13-08-2023","Casa":"Guarani","GC":"0","GF":"1","Fora":"Juventude","Res":"VV","PC":0,"PF":3,"J":225},{"Comp":"S\u00e9rie B","Temp":2023,"Data":"13-08-2023","Casa":"Vit\u00f3ria","GC":"1","GF":"0","Fora":"Cear\u00e1","Res":"VC","PC":3,"PF":0,"J":226},{"Comp":"S\u00e9rie B","Temp":2023,"Data":"13-08-2023","Casa":"Chapecoense","GC":"0","GF":"1","Fora":"Atl\u00e9tico-GO","Res":"VV","PC":0,"PF":3,"J":227},{"Comp":"S\u00e9rie B","Temp":2023,"Data":"14-08-2023","Casa":"ABC","GC":"1","GF":"1","Fora":"Ituano","Res":"E","PC":1,"PF":1,"J":228},{"Comp":"S\u00e9rie B","Temp":2023,"Data":"17-08-2023","Casa":"Vila Nova-GO","GC":"2","GF":"0","Fora":"Mirassol","Res":"VC","PC":3,"PF":0,"J":229},{"Comp":"S\u00e9rie B","Temp":2023,"Data":"17-08-2023","Casa":"Londrina","GC":"0","GF":"2","Fora":"Atl\u00e9tico-GO","Res":"VV","PC":0,"PF":3,"J":230},{"Comp":"S\u00e9rie B","Temp":2023,"Data":"18-08-2023","Casa":"Guarani","GC":"3","GF":"1","Fora":"Sport","Res":"VC","PC":3,"PF":0,"J":231},{"Comp":"S\u00e9rie B","Temp":2023,"Data":"18-08-2023","Casa":"Vit\u00f3ria","GC":"2","GF":"0","Fora":"Botafogo-SP","Res":"VC","PC":3,"PF":0,"J":232},{"Comp":"S\u00e9rie B","Temp":2023,"Data":"19-08-2023","Casa":"Ava\u00ed","GC":"4","GF":"2","Fora":"Tombense","Res":"VC","PC":3,"PF":0,"J":233},{"Comp":"S\u00e9rie B","Temp":2023,"Data":"19-08-2023","Casa":"Ituano","GC":"3","GF":"0","Fora":"Crici\u00fama","Res":"VC","PC":3,"PF":0,"J":234},{"Comp":"S\u00e9rie B","Temp":2023,"Data":"19-08-2023","Casa":"Juventude","GC":"0","GF":"0","Fora":"Sampaio Corr\u00eaa","Res":"E","PC":1,"PF":1,"J":235},{"Comp":"S\u00e9rie B","Temp":2023,"Data":"19-08-2023","Casa":"ABC","GC":"1","GF":"2","Fora":"CRB","Res":"VV","PC":0,"PF":3,"J":236},{"Comp":"S\u00e9rie B","Temp":2023,"Data":"20-08-2023","Casa":"Novorizontino","GC":"1","GF":"2","Fora":"Chapecoense","Res":"VV","PC":0,"PF":3,"J":237},{"Comp":"S\u00e9rie B","Temp":2023,"Data":"20-08-2023","Casa":"Cear\u00e1","GC":"1","GF":"1","Fora":"Ponte Preta","Res":"E","PC":1,"PF":1,"J":238},{"Comp":"S\u00e9rie B","Temp":2023,"Data":"22-08-2023","Casa":"Crici\u00fama","GC":"1","GF":"0","Fora":"Vila Nova-GO","Res":"VC","PC":3,"PF":0,"J":239},{"Comp":"S\u00e9rie B","Temp":2023,"Data":"22-08-2023","Casa":"Mirassol","GC":"0","GF":"1","Fora":"Juventude","Res":"VV","PC":0,"PF":3,"J":240},{"Comp":"S\u00e9rie B","Temp":2023,"Data":"23-08-2023","Casa":"Botafogo-SP","GC":"1","GF":"2","Fora":"Chapecoense","Res":"VV","PC":0,"PF":3,"J":241},{"Comp":"S\u00e9rie B","Temp":2023,"Data":"23-08-2023","Casa":"CRB","GC":"1","GF":"1","Fora":"Ava\u00ed","Res":"E","PC":1,"PF":1,"J":242},{"Comp":"S\u00e9rie B","Temp":2023,"Data":"25-08-2023","Casa":"Ponte Preta","GC":"1","GF":"0","Fora":"Londrina","Res":"VC","PC":3,"PF":0,"J":243},{"Comp":"S\u00e9rie B","Temp":2023,"Data":"25-08-2023","Casa":"Sport","GC":"1","GF":"2","Fora":"Ituano","Res":"VV","PC":0,"PF":3,"J":244},{"Comp":"S\u00e9rie B","Temp":2023,"Data":"26-08-2023","Casa":"Tombense","GC":"2","GF":"2","Fora":"Cear\u00e1","Res":"E","PC":1,"PF":1,"J":245},{"Comp":"S\u00e9rie B","Temp":2023,"Data":"26-08-2023","Casa":"Sampaio Corr\u00eaa","GC":"1","GF":"1","Fora":"Guarani","Res":"E","PC":1,"PF":1,"J":246},{"Comp":"S\u00e9rie B","Temp":2023,"Data":"26-08-2023","Casa":"CRB","GC":"1","GF":"0","Fora":"Novorizontino","Res":"VC","PC":3,"PF":0,"J":247},{"Comp":"S\u00e9rie B","Temp":2023,"Data":"27-08-2023","Casa":"Atl\u00e9tico-GO","GC":"0","GF":"0","Fora":"Vit\u00f3ria","Res":"E","PC":1,"PF":1,"J":248},{"Comp":"S\u00e9rie B","Temp":2023,"Data":"27-08-2023","Casa":"Chapecoense","GC":"0","GF":"0","Fora":"Ava\u00ed","Res":"E","PC":1,"PF":1,"J":249}]